shadow_drive-0.0.0.dist-info/METADATA
shadow_drive-0.0.0.dist-info/WHEEL
shadow_drive.libs/libcrypto-d578cd7f.so.1.1
shadow_drive.libs/libssl-578d2f9a.so.1.1
shadow_drive/__init__.py
shadow_drive/shadow_drive.cpython-310-x86_64-linux-gnu.so
shadow_drive-0.0.0.dist-info/RECORD
