Metadata-Version: 2.1
Name: shadow-drive
Version: 0.0.0
Classifier: Programming Language :: Rust
Classifier: Programming Language :: Python :: Implementation :: CPython
Classifier: Programming Language :: Python :: Implementation :: PyPy
Summary: The Python SDK for GenesysGo's Shadow Drive
Author: Cavey Cool <caveycool@gmail.com>, Tracy <tracy@tracycodes.com>
Author-email: Cavey Cool <caveycool@gmail.com>, Tracy <tracy@tracycodes.com>
License: MIT OR Apache-2.0
Requires-Python: >=3.7
Project-URL: Source Code, https://github.com/GenesysGo/shadow-drive-rust
